{
 "cells": [
  {
   "cell_type": "code",
   "execution_count": 19,
   "id": "288caae3",
   "metadata": {},
   "outputs": [],
   "source": [
    "from visualizer import get_local\n",
    "import torch\n",
    "get_local.activate()"
   ]
  },
  {
   "cell_type": "code",
   "execution_count": 20,
   "id": "eebd1991",
   "metadata": {},
   "outputs": [],
   "source": [
    "t = torch.ones(2, 3, requires_grad=True, device='cpu')\n",
    "\n",
    "class c1:\n",
    "    def __init__(self, value):\n",
    "        self.value = value\n",
    "\n",
    "    def f(self, x):\n",
    "        return torch.ones(2, x, requires_grad=True)\n",
    "    \n",
    "    @get_local('result')\n",
    "    def get_value(self):\n",
    "        result = self.f(self.value)\n",
    "        return result\n",
    "    \n",
    "@get_local('x2', 'y2', 'z2')\n",
    "def fun2(v=1):\n",
    "    y2 = {'k': v *2}\n",
    "    x2 = [v]\n",
    "    z2 = (v * 3)\n",
    "    return x2, y2, z2"
   ]
  },
  {
   "cell_type": "code",
   "execution_count": 21,
   "id": "9a46ba33",
   "metadata": {},
   "outputs": [
    {
     "data": {
      "text/plain": [
       "([tensor([[1., 1., 1.],\n",
       "          [1., 1., 1.]], requires_grad=True)],\n",
       " {'k': tensor([[2., 2., 2.],\n",
       "          [2., 2., 2.]], grad_fn=<MulBackward0>)},\n",
       " tensor([[3., 3., 3.],\n",
       "         [3., 3., 3.]], grad_fn=<MulBackward0>))"
      ]
     },
     "execution_count": 21,
     "metadata": {},
     "output_type": "execute_result"
    }
   ],
   "source": [
    "c = c1(4)\n",
    "c.get_value()\n",
    "\n",
    "fun2(5)\n",
    "fun2(t)"
   ]
  },
  {
   "cell_type": "code",
   "execution_count": 22,
   "id": "8dcceb56",
   "metadata": {},
   "outputs": [],
   "source": [
    "@get_local('closure_var')\n",
    "def create_closure_test():\n",
    "    \"\"\"创建一个包含闭包变量的测试案例\"\"\"\n",
    "    # 闭包变量 (将被嵌套函数引用)\n",
    "    closure_var = 10\n",
    "    var = 1\n",
    "    \n",
    "    def nested_func():\n",
    "        \"\"\"嵌套函数：修改并返回闭包变量\"\"\"\n",
    "        nonlocal closure_var  # 声明为闭包变量\n",
    "        closure_var += 1\n",
    "        return closure_var\n",
    "    \n",
    "    return nested_func()\n",
    "\n",
    "def create_plain_test(arg1 = 1):\n",
    "    var = 1\n",
    "    li = [1, 2, 3]\n",
    "    return var, li, arg1"
   ]
  },
  {
   "cell_type": "markdown",
   "id": "64ca91e1",
   "metadata": {},
   "source": [
    "create_closure_test 和 create_plain_test 中变量类型是不同的"
   ]
  },
  {
   "cell_type": "code",
   "execution_count": 23,
   "id": "90325ec4",
   "metadata": {},
   "outputs": [
    {
     "name": "stdout",
     "output_type": "stream",
     "text": [
      "co_argcount:\t0\n",
      "co_cellvars:\t()\n",
      "co_code:\tb'y\\x0e\\x88\\x01|\\x00|\\x01\\x8e\\x01}\\x02W\\x00nT\\x04\\x00t\\x00k\\nrb\\x01\\x00}\\x03\\x01\\x00z6t\\x01d\\x01|\\x03\\x83\\x02\\x01\\x00t\\x01d\\x02\\x83\\x01\\x01\\x00t\\x01t\\x02\\xa0\\x03\\x88\\x01j\\x04\\xa1\\x01\\x83\\x01\\x01\\x00t\\x01\\x88\\x00\\x83\\x01\\x01\\x00t\\x05d\\x03\\x83\\x01\\x01\\x00W\\x00d\\x00d\\x00}\\x03~\\x03X\\x00Y\\x00n\\x02X\\x00|\\x02d\\x04\\x19\\x00|\\x02d\\x03d\\x00\\x85\\x02\\x19\\x00\\x02\\x00}\\x04}\\x05g\\x00}\\x06x\\x90|\\x05D\\x00]\\x88}\\x07t\\x06|\\x07d\\x05\\x83\\x02r\\xaa|\\x06\\xa0\\x07|\\x07\\xa0\\x08\\xa1\\x00\\xa0\\t\\xa1\\x00\\xa0\\n\\xa1\\x00\\xa1\\x01\\x01\\x00q\\x84t\\x0b|\\x07t\\x0c\\x83\\x02s\\xc0t\\x0b|\\x07t\\r\\x83\\x02\\x90\\x01r\\x02g\\x00}\\x08x0|\\x07D\\x00](}\\t|\\x08\\xa0\\x07t\\x06|\\td\\x05\\x83\\x02r\\xec|\\t\\xa0\\x08\\xa1\\x00\\xa0\\t\\xa1\\x00\\xa0\\n\\xa1\\x00n\\x02|\\t\\xa1\\x01\\x01\\x00q\\xcaW\\x00|\\x06\\xa0\\x07|\\x08\\xa1\\x01\\x01\\x00q\\x84|\\x06\\xa0\\x07|\\x07\\xa1\\x01\\x01\\x00q\\x84W\\x00t\\x0e\\x88\\x02\\x83\\x01j\\x0f\\x88\\x01j\\x10\\x19\\x00\\xa0\\x07|\\x06\\xa1\\x01\\x01\\x00|\\x04S\\x00'\n",
      "co_consts:\t(None, 'UnboundLocalError:', 'Function code And Extra code: ', 1, 0, 'detach')\n",
      "co_filename:\t/home/lxk/Desktop/visual/visualizer.py\n",
      "co_firstlineno:\t69\n",
      "co_flags:\t31\n",
      "co_freevars:\t('extra_code', 'func', 'self')\n",
      "co_kwonlyargcount:\t0\n",
      "co_lnotab:\tb'\\x00\\x01\\x02\\x01\\x0e\\x01\\x10\\x01\\n\\x01\\x08\\x01\\x10\\x01\\x08\\x01\\x1a\\x01\\x16\\x01\\x04\\x01\\n\\x01\\n\\x01\\x18\\x01\\x16\\x01\\x04\\x01\\n\\x01(\\x01\\x0c\\x02\\x0e\\x01\\x16\\x01'\n",
      "co_name:\twrapper\n",
      "co_names:\t('UnboundLocalError', 'print', 'Bytecode', 'from_code', '__code__', 'exit', 'hasattr', 'append', 'detach', 'cpu', 'numpy', 'isinstance', 'list', 'tuple', 'type', 'cache', '__qualname__')\n",
      "co_nlocals:\t10\n",
      "co_stacksize:\t10\n",
      "co_varnames:\t('args', 'kwargs', 'result', 'e', 'res', 'values', 'cache_list', 'value', 'vals', 'val')\n"
     ]
    }
   ],
   "source": [
    "fun = create_closure_test\n",
    "code = fun.__code__\n",
    "\n",
    "for attr in dir(code):\n",
    "    if attr.startswith('co_'):\n",
    "        print(f\"{attr}:\\t{getattr(code, attr)}\")"
   ]
  },
  {
   "cell_type": "code",
   "execution_count": 24,
   "id": "54a37e15",
   "metadata": {},
   "outputs": [
    {
     "data": {
      "text/plain": [
       "{'c1.get_value': [['result'],\n",
       "  [array([[1., 1., 1., 1.],\n",
       "          [1., 1., 1., 1.]], dtype=float32)]],\n",
       " 'fun2': [['x2', 'y2', 'z2'],\n",
       "  [[5], {'k': 10}, 15],\n",
       "  [[array([[1., 1., 1.],\n",
       "           [1., 1., 1.]], dtype=float32)],\n",
       "   {'k': tensor([[2., 2., 2.],\n",
       "            [2., 2., 2.]], grad_fn=<MulBackward0>)},\n",
       "   array([[3., 3., 3.],\n",
       "          [3., 3., 3.]], dtype=float32)]],\n",
       " 'create_closure_test': [['closure_var']]}"
      ]
     },
     "execution_count": 24,
     "metadata": {},
     "output_type": "execute_result"
    }
   ],
   "source": [
    "get_local.cache"
   ]
  },
  {
   "cell_type": "code",
   "execution_count": 25,
   "id": "1b1a050c",
   "metadata": {},
   "outputs": [],
   "source": [
    "get_local.clear()"
   ]
  },
  {
   "cell_type": "code",
   "execution_count": 26,
   "id": "d9cae21e",
   "metadata": {},
   "outputs": [
    {
     "name": "stdout",
     "output_type": "stream",
     "text": [
      "Disassembly of __init__:\n",
      "  5           0 LOAD_FAST                1 (value)\n",
      "              2 LOAD_FAST                0 (self)\n",
      "              4 STORE_ATTR               0 (value)\n",
      "              6 LOAD_CONST               0 (None)\n",
      "              8 RETURN_VALUE\n",
      "\n",
      "Disassembly of f:\n",
      "  8           0 LOAD_GLOBAL              0 (torch)\n",
      "              2 LOAD_ATTR                1 (ones)\n",
      "              4 LOAD_CONST               1 (2)\n",
      "              6 LOAD_FAST                1 (x)\n",
      "              8 LOAD_CONST               2 (True)\n",
      "             10 LOAD_CONST               3 (('requires_grad',))\n",
      "             12 CALL_FUNCTION_KW         3\n",
      "             14 RETURN_VALUE\n",
      "\n",
      "Disassembly of get_value:\n",
      " 70           0 SETUP_EXCEPT            14 (to 16)\n",
      "\n",
      " 71           2 LOAD_DEREF               1 (func)\n",
      "              4 LOAD_FAST                0 (args)\n",
      "              6 LOAD_FAST                1 (kwargs)\n",
      "              8 CALL_FUNCTION_EX         1\n",
      "             10 STORE_FAST               2 (result)\n",
      "             12 POP_BLOCK\n",
      "             14 JUMP_FORWARD            84 (to 100)\n",
      "\n",
      " 72     >>   16 DUP_TOP\n",
      "             18 LOAD_GLOBAL              0 (UnboundLocalError)\n",
      "             20 COMPARE_OP              10 (exception match)\n",
      "             22 POP_JUMP_IF_FALSE       98\n",
      "             24 POP_TOP\n",
      "             26 STORE_FAST               3 (e)\n",
      "             28 POP_TOP\n",
      "             30 SETUP_FINALLY           54 (to 86)\n",
      "\n",
      " 73          32 LOAD_GLOBAL              1 (print)\n",
      "             34 LOAD_CONST               1 ('UnboundLocalError:')\n",
      "             36 LOAD_FAST                3 (e)\n",
      "             38 CALL_FUNCTION            2\n",
      "             40 POP_TOP\n",
      "\n",
      " 74          42 LOAD_GLOBAL              1 (print)\n",
      "             44 LOAD_CONST               2 ('Function code And Extra code: ')\n",
      "             46 CALL_FUNCTION            1\n",
      "             48 POP_TOP\n",
      "\n",
      " 75          50 LOAD_GLOBAL              1 (print)\n",
      "             52 LOAD_GLOBAL              2 (Bytecode)\n",
      "             54 LOAD_METHOD              3 (from_code)\n",
      "             56 LOAD_DEREF               1 (func)\n",
      "             58 LOAD_ATTR                4 (__code__)\n",
      "             60 CALL_METHOD              1\n",
      "             62 CALL_FUNCTION            1\n",
      "             64 POP_TOP\n",
      "\n",
      " 76          66 LOAD_GLOBAL              1 (print)\n",
      "             68 LOAD_DEREF               0 (extra_code)\n",
      "             70 CALL_FUNCTION            1\n",
      "             72 POP_TOP\n",
      "\n",
      " 77          74 LOAD_GLOBAL              5 (exit)\n",
      "             76 LOAD_CONST               3 (1)\n",
      "             78 CALL_FUNCTION            1\n",
      "             80 POP_TOP\n",
      "             82 POP_BLOCK\n",
      "             84 LOAD_CONST               0 (None)\n",
      "        >>   86 LOAD_CONST               0 (None)\n",
      "             88 STORE_FAST               3 (e)\n",
      "             90 DELETE_FAST              3 (e)\n",
      "             92 END_FINALLY\n",
      "             94 POP_EXCEPT\n",
      "             96 JUMP_FORWARD             2 (to 100)\n",
      "        >>   98 END_FINALLY\n",
      "\n",
      " 78     >>  100 LOAD_FAST                2 (result)\n",
      "            102 LOAD_CONST               4 (0)\n",
      "            104 BINARY_SUBSCR\n",
      "            106 LOAD_FAST                2 (result)\n",
      "            108 LOAD_CONST               3 (1)\n",
      "            110 LOAD_CONST               0 (None)\n",
      "            112 BUILD_SLICE              2\n",
      "            114 BINARY_SUBSCR\n",
      "            116 ROT_TWO\n",
      "            118 STORE_FAST               4 (res)\n",
      "            120 STORE_FAST               5 (values)\n",
      "\n",
      " 79         122 BUILD_LIST               0\n",
      "            124 STORE_FAST               6 (cache_list)\n",
      "\n",
      " 80         126 SETUP_LOOP             144 (to 272)\n",
      "            128 LOAD_FAST                5 (values)\n",
      "            130 GET_ITER\n",
      "        >>  132 FOR_ITER               136 (to 270)\n",
      "            134 STORE_FAST               7 (value)\n",
      "\n",
      " 81         136 LOAD_GLOBAL              6 (hasattr)\n",
      "            138 LOAD_FAST                7 (value)\n",
      "            140 LOAD_CONST               5 ('detach')\n",
      "            142 CALL_FUNCTION            2\n",
      "            144 POP_JUMP_IF_FALSE      170\n",
      "\n",
      " 82         146 LOAD_FAST                6 (cache_list)\n",
      "            148 LOAD_METHOD              7 (append)\n",
      "            150 LOAD_FAST                7 (value)\n",
      "            152 LOAD_METHOD              8 (detach)\n",
      "            154 CALL_METHOD              0\n",
      "            156 LOAD_METHOD              9 (cpu)\n",
      "            158 CALL_METHOD              0\n",
      "            160 LOAD_METHOD             10 (numpy)\n",
      "            162 CALL_METHOD              0\n",
      "            164 CALL_METHOD              1\n",
      "            166 POP_TOP\n",
      "            168 JUMP_ABSOLUTE          132\n",
      "\n",
      " 83     >>  170 LOAD_GLOBAL             11 (isinstance)\n",
      "            172 LOAD_FAST                7 (value)\n",
      "            174 LOAD_GLOBAL             12 (list)\n",
      "            176 CALL_FUNCTION            2\n",
      "            178 POP_JUMP_IF_TRUE       192\n",
      "            180 LOAD_GLOBAL             11 (isinstance)\n",
      "            182 LOAD_FAST                7 (value)\n",
      "            184 LOAD_GLOBAL             13 (tuple)\n",
      "            186 CALL_FUNCTION            2\n",
      "            188 EXTENDED_ARG             1\n",
      "            190 POP_JUMP_IF_FALSE      258\n",
      "\n",
      " 84     >>  192 BUILD_LIST               0\n",
      "            194 STORE_FAST               8 (vals)\n",
      "\n",
      " 85         196 SETUP_LOOP              48 (to 246)\n",
      "            198 LOAD_FAST                7 (value)\n",
      "            200 GET_ITER\n",
      "        >>  202 FOR_ITER                40 (to 244)\n",
      "            204 STORE_FAST               9 (val)\n",
      "\n",
      " 86         206 LOAD_FAST                8 (vals)\n",
      "            208 LOAD_METHOD              7 (append)\n",
      "            210 LOAD_GLOBAL              6 (hasattr)\n",
      "            212 LOAD_FAST                9 (val)\n",
      "            214 LOAD_CONST               5 ('detach')\n",
      "            216 CALL_FUNCTION            2\n",
      "            218 POP_JUMP_IF_FALSE      236\n",
      "            220 LOAD_FAST                9 (val)\n",
      "            222 LOAD_METHOD              8 (detach)\n",
      "            224 CALL_METHOD              0\n",
      "            226 LOAD_METHOD              9 (cpu)\n",
      "            228 CALL_METHOD              0\n",
      "            230 LOAD_METHOD             10 (numpy)\n",
      "            232 CALL_METHOD              0\n",
      "            234 JUMP_FORWARD             2 (to 238)\n",
      "        >>  236 LOAD_FAST                9 (val)\n",
      "        >>  238 CALL_METHOD              1\n",
      "            240 POP_TOP\n",
      "            242 JUMP_ABSOLUTE          202\n",
      "        >>  244 POP_BLOCK\n",
      "\n",
      " 87     >>  246 LOAD_FAST                6 (cache_list)\n",
      "            248 LOAD_METHOD              7 (append)\n",
      "            250 LOAD_FAST                8 (vals)\n",
      "            252 CALL_METHOD              1\n",
      "            254 POP_TOP\n",
      "            256 JUMP_ABSOLUTE          132\n",
      "\n",
      " 89     >>  258 LOAD_FAST                6 (cache_list)\n",
      "            260 LOAD_METHOD              7 (append)\n",
      "            262 LOAD_FAST                7 (value)\n",
      "            264 CALL_METHOD              1\n",
      "            266 POP_TOP\n",
      "            268 JUMP_ABSOLUTE          132\n",
      "        >>  270 POP_BLOCK\n",
      "\n",
      " 90     >>  272 LOAD_GLOBAL             14 (type)\n",
      "            274 LOAD_DEREF               2 (self)\n",
      "            276 CALL_FUNCTION            1\n",
      "            278 LOAD_ATTR               15 (cache)\n",
      "            280 LOAD_DEREF               1 (func)\n",
      "            282 LOAD_ATTR               16 (__qualname__)\n",
      "            284 BINARY_SUBSCR\n",
      "            286 LOAD_METHOD              7 (append)\n",
      "            288 LOAD_FAST                6 (cache_list)\n",
      "            290 CALL_METHOD              1\n",
      "            292 POP_TOP\n",
      "\n",
      " 91         294 LOAD_FAST                4 (res)\n",
      "            296 RETURN_VALUE\n",
      "\n"
     ]
    }
   ],
   "source": [
    "import dis\n",
    "dis.dis(c1)"
   ]
  }
 ],
 "metadata": {
  "kernelspec": {
   "display_name": "openmmlab",
   "language": "python",
   "name": "python3"
  },
  "language_info": {
   "codemirror_mode": {
    "name": "ipython",
    "version": 3
   },
   "file_extension": ".py",
   "mimetype": "text/x-python",
   "name": "python",
   "nbconvert_exporter": "python",
   "pygments_lexer": "ipython3",
   "version": "3.7.12"
  }
 },
 "nbformat": 4,
 "nbformat_minor": 5
}
